aaypyutil/__init__.py
aaypyutil/func_util.py
aaypyutil/log_util.py
aaypyutil-1.0.3.dist-info/LICENSE
aaypyutil-1.0.3.dist-info/METADATA
aaypyutil-1.0.3.dist-info/WHEEL
aaypyutil-1.0.3.dist-info/top_level.txt
aaypyutil-1.0.3.dist-info/RECORD
