Metadata-Version: 2.1
Name: aaypyutil
Version: 1.0.3
Summary: Common python util functions
Home-page: https://github.com/aayushuppal/aaypyutil
Author: Aayush Uppal
Author-email: aayuppal@gmail.com
License: MIT
Platform: UNKNOWN
Classifier: License :: OSI Approved :: MIT License
Classifier: Programming Language :: Python
Classifier: Programming Language :: Python :: 2
Classifier: Programming Language :: Python :: 3
